ovos_skill_dictation/LICENSE
ovos_skill_dictation/MANIFEST.in
ovos_skill_dictation/README.md
ovos_skill_dictation/__init__.py
ovos_skill_dictation/requirements.txt
ovos_skill_dictation/version.py
ovos_skill_dictation/locale/ca-es/skill.json
ovos_skill_dictation/locale/ca-es/dialogs/already_dictating.dialog
ovos_skill_dictation/locale/ca-es/dialogs/dictation.dialog
ovos_skill_dictation/locale/ca-es/dialogs/not_dictating.dialog
ovos_skill_dictation/locale/ca-es/dialogs/start.dialog
ovos_skill_dictation/locale/ca-es/dialogs/stop.dialog
ovos_skill_dictation/locale/ca-es/intents/StopKeyword.voc
ovos_skill_dictation/locale/ca-es/intents/start_dictation.intent
ovos_skill_dictation/locale/ca-es/intents/stop_dictation.intent
ovos_skill_dictation/locale/da/skill.json
ovos_skill_dictation/locale/da/dialogs/already_dictating.dialog
ovos_skill_dictation/locale/da/dialogs/dictation.dialog
ovos_skill_dictation/locale/da/dialogs/not_dictating.dialog
ovos_skill_dictation/locale/da/dialogs/start.dialog
ovos_skill_dictation/locale/da/dialogs/stop.dialog
ovos_skill_dictation/locale/da/intents/StopKeyword.voc
ovos_skill_dictation/locale/da/intents/start_dictation.intent
ovos_skill_dictation/locale/da/intents/stop_dictation.intent
ovos_skill_dictation/locale/de-de/skill.json
ovos_skill_dictation/locale/de-de/dialogs/already_dictating.dialog
ovos_skill_dictation/locale/de-de/dialogs/dictation.dialog
ovos_skill_dictation/locale/de-de/dialogs/not_dictating.dialog
ovos_skill_dictation/locale/de-de/dialogs/start.dialog
ovos_skill_dictation/locale/de-de/dialogs/stop.dialog
ovos_skill_dictation/locale/de-de/intents/StopKeyword.voc
ovos_skill_dictation/locale/de-de/intents/start_dictation.intent
ovos_skill_dictation/locale/de-de/intents/stop_dictation.intent
ovos_skill_dictation/locale/en-us/skill.json
ovos_skill_dictation/locale/en-us/dialogs/already_dictating.dialog
ovos_skill_dictation/locale/en-us/dialogs/dictation.dialog
ovos_skill_dictation/locale/en-us/dialogs/not_dictating.dialog
ovos_skill_dictation/ovos_skill_dictation.egg-info/PKG-INFO
ovos_skill_dictation/ovos_skill_dictation.egg-info/SOURCES.txt
ovos_skill_dictation/ovos_skill_dictation.egg-info/dependency_links.txt
ovos_skill_dictation/ovos_skill_dictation.egg-info/entry_points.txt
ovos_skill_dictation/ovos_skill_dictation.egg-info/requires.txt
ovos_skill_dictation/ovos_skill_dictation.egg-info/top_level.txt
ovos_skill_dictation-0.2.19.dist-info/LICENSE
ovos_skill_dictation-0.2.19.dist-info/METADATA
ovos_skill_dictation-0.2.19.dist-info/WHEEL
ovos_skill_dictation-0.2.19.dist-info/entry_points.txt
ovos_skill_dictation-0.2.19.dist-info/top_level.txt
ovos_skill_dictation-0.2.19.dist-info/RECORD
