Metadata-Version: 2.1
Name: ovos-skill-dictation
Version: 0.2.19
Summary: DictationSkill
Home-page: https://github.com/OVOSHatchery/ovos-skill-dictation
Author: OpenVoiceOS
Author-email: jarbasai@mailfence.com
License: Apache2.0
Keywords: ovos skill plugin
License-File: LICENSE
Requires-Dist: ovos-workshop<8.0.0,>=7.0.0
